ansys/conceptev/core/__init__.py
ansys/conceptev/core/app.py
ansys/conceptev/core/auth.py
ansys/conceptev/core/exceptions.py
ansys/conceptev/core/ocm.py
ansys/conceptev/core/progress.py
ansys/conceptev/core/resources/config.toml
ansys/conceptev/core/responses.py
ansys/conceptev/core/settings.py
ansys_conceptev_core-0.10.2.dist-info/METADATA
ansys_conceptev_core-0.10.2.dist-info/WHEEL
ansys_conceptev_core-0.10.2.dist-info/licenses/AUTHORS
ansys_conceptev_core-0.10.2.dist-info/licenses/LICENSE
ansys_conceptev_core-0.10.2.dist-info/RECORD
