Metadata-Version: 2.4
Name: ansys-conceptev-core
Version: 0.10.2
Summary: A Python wrapper for Ansys Conceptev core
License: MIT
License-File: AUTHORS
License-File: LICENSE
Keywords: Ansys,Concept EV,Electric Powertrain
Author: ANSYS, Inc.
Author-email: pyansys.core@ansys.com
Maintainer: ANSYS, Inc.
Maintainer-email: pyansys.core@ansys.com
Requires-Python: >=3.10,<4.0
Classifier: Development Status :: 4 - Beta
Classifier: Intended Audience :: Science/Research
Classifier: License :: OSI Approved :: MIT License
Classifier: Operating System :: OS Independent
Classifier: Programming Language :: Python :: 3
Classifier: Programming Language :: Python :: 3.10
Classifier: Programming Language :: Python :: 3.11
Classifier: Programming Language :: Python :: 3.12
Classifier: Programming Language :: Python :: 3.13
Classifier: Programming Language :: Python :: 3.14
Requires-Dist: async-timeout (>=4) ; python_version < "3.11"
Requires-Dist: email-validator (>=2.2.0,<3.0.0)
Requires-Dist: httpx (>=0.26.0)
Requires-Dist: msal (>=1.29.0)
Requires-Dist: msal-extensions (>=1.2.0)
Requires-Dist: pydantic-settings (>=2.7.1,<3.0.0)
Requires-Dist: python-dotenv (>=1.0.0)
Requires-Dist: tenacity (>=8.2.3,<10.0.0)
Requires-Dist: tomli (>=2.0.1) ; python_version < "3.11"
Requires-Dist: truststore (>=0.10.4,<0.11.0) ; python_version >= "3.10" and python_version < "4.0"
Requires-Dist: websockets (>=13.0.1)
Project-URL: Documentation, https://conceptev.docs.pyansys.com
Project-URL: Repository, https://github.com/ansys/pyconceptev
